PyGnuplot.py
PyGnuplot-0.12.3.dist-info/LICENSE
PyGnuplot-0.12.3.dist-info/METADATA
PyGnuplot-0.12.3.dist-info/WHEEL
PyGnuplot-0.12.3.dist-info/top_level.txt
PyGnuplot-0.12.3.dist-info/RECORD
