Metadata-Version: 2.1
Name: PyGnuplot
Version: 0.12.3
Summary: Python Gnuplot wrapper
Home-page: https://github.com/benschneider/PyGnuplot
Download-URL: https://github.com/benschneider/PyGnuplot/archive/0.12.3.tar.gz
Author: Ben Schneider
Author-email: 
License: MIT
Keywords: gnuplot,plot
Classifier: Topic :: Scientific/Engineering
Classifier: License :: OSI Approved :: MIT License
Classifier: Programming Language :: Python :: 2.6
Classifier: Programming Language :: Python :: 2.7
Classifier: Programming Language :: Python :: 3.5
Classifier: Programming Language :: Python :: 3.6
Classifier: Programming Language :: Python :: 3.7
Classifier: Programming Language :: Python :: 3.8
Classifier: Programming Language :: Python :: 3.9
Classifier: Programming Language :: Python :: 3.10
Classifier: Development Status :: 4 - Beta
License-File: LICENSE
